Task_5 /IP/PWM/RTL/pwm_ip.v
module pwm_ip (
    input  wire        clk,
    input  wire        rst_n,

    input  wire        bus_we,
    input  wire [31:0] bus_addr,
    input  wire [31:0] bus_wdata,
    output reg  [31:0] bus_rdata,

    output reg         pwm_out
);

    localparam CTRL   = 32'h00;
    localparam PERIOD = 32'h04;
    localparam DUTY   = 32'h08;
    localparam STATUS = 32'h0C;

    reg        en;
    reg        pol;
    reg [31:0] period_reg;
    reg [31:0] duty_reg;
    reg [31:0] cnt;

    // Register write
    always @(posedge clk or negedge rst_n) begin
        if (!rst_n) begin
            en         <= 0;
            pol        <= 0;
            period_reg <= 1;
            duty_reg   <= 0;
        end else if (bus_we) begin
            case (bus_addr)
                CTRL: begin
                    en  <= bus_wdata[0];
                    pol <= bus_wdata[1];
                end
                PERIOD: if (bus_wdata >= 1)
                    period_reg <= bus_wdata;
                DUTY:
                    duty_reg <= bus_wdata;
            endcase
        end
    end

    // PWM counter
    always @(posedge clk or negedge rst_n) begin
        if (!rst_n)
            cnt <= 0;
        else if (!en)
            cnt <= 0;
        else if (cnt == period_reg - 1)
            cnt <= 0;
        else
            cnt <= cnt + 1;
    end

    // PWM output
    always @(*) begin
        if (!en)
            pwm_out = pol ? 1'b1 : 1'b0;
        else if (cnt < duty_reg)
            pwm_out = pol ? 1'b0 : 1'b1;
        else
            pwm_out = pol ? 1'b1 : 1'b0;
    end

    // Register read
    always @(*) begin
        case (bus_addr)
            CTRL:   bus_rdata = {30'd0, pol, en};
            PERIOD: bus_rdata = period_reg;
            DUTY:   bus_rdata = duty_reg;
            STATUS: bus_rdata = cnt;
            default: bus_rdata = 32'd0;
        endcase
    end

endmodule

Task_4/test/pwm_tb.v
`timescale 1ns/1ps
module pwm_tb;

reg clk = 0;
reg rst_n = 0;
reg bus_we;
reg [31:0] bus_addr;
reg [31:0] bus_wdata;
wire pwm_out;

always #5 clk = ~clk;  // 100 MHz clock

pwm_ip dut (
    .clk(clk),
    .rst_n(rst_n),
    .bus_we(bus_we),
    .bus_addr(bus_addr),
    .bus_wdata(bus_wdata),
    .bus_rdata(),
    .pwm_out(pwm_out)
);

task write;
input [31:0] addr, data;
begin
    bus_addr  = addr;
    bus_wdata = data;
    bus_we    = 1;
    #10 bus_we = 0;
end
endtask

initial begin
    $dumpfile("pwm.vcd");
    $dumpvars(0, pwm_tb);

    #20 rst_n = 1;

    write(32'h04, 20); // PERIOD = 20
    write(32'h08, 10); // DUTY   = 10 (50%)
    write(32'h00, 1);  // CTRL.EN = 1

    #400;
    $finish;
end

endmodule

Task_4/pwm.vcd
$date
	Tue Jan  6 18:52:16 2026
$end
$version
	Icarus Verilog
$end
$timescale
	1ps
$end
$scope module pwm_tb $end
$var wire 1 ! pwm_out $end
$var reg 32 " bus_addr [31:0] $end
$var reg 32 # bus_wdata [31:0] $end
$var reg 1 $ bus_we $end
$var reg 1 % clk $end
$var reg 1 & rst_n $end
$scope module dut $end
$var wire 32 ' bus_addr [31:0] $end
$var wire 32 ( bus_wdata [31:0] $end
$var wire 1 $ bus_we $end
$var wire 1 % clk $end
$var wire 1 & rst_n $end
$var parameter 32 ) CTRL $end
$var parameter 32 * DUTY $end
$var parameter 32 + PERIOD $end
$var parameter 32 , STATUS $end
$var reg 32 - bus_rdata [31:0] $end
$var reg 32 . cnt [31:0] $end
$var reg 32 / duty_reg [31:0] $end
$var reg 1 0 en $end
$var reg 32 1 period_reg [31:0] $end
$var reg 1 2 pol $end
$var reg 1 ! pwm_out $end
$upscope $end
$scope task write $end
$var reg 32 3 addr [31:0] $end
$var reg 32 4 data [31:0] $end
$upscope $end
$upscope $end
$enddefinitions $end
$comment Show the parameter values. $end
$dumpall
b1100 ,
b100 +
b1000 *
b0 )
$end
#0
$dumpvars
bx 4
bx 3
02
b1 1
00
b0 /
b0 .
b0 -
bx (
bx '
0&
0%
x$
bx #
bx "
0!
$end
#5000
1%
#10000
0%
#15000
1%
#20000
b1 -
0%
1$
b10100 #
b10100 (
b100 "
b100 '
b10100 4
b100 3
1&
#25000
b10100 -
b10100 1
1%
#30000
b0 -
0%
b1010 #
b1010 (
b1000 "
b1000 '
b1010 4
b1000 3
1$
#35000
b1010 -
b1010 /
1%
#40000
b0 -
0%
b1 #
b1 (
b0 "
b0 '
b1 4
b0 3
1$
#45000
b1 -
1!
10
1%
#50000
0%
0$
#55000
b1 .
1%
#60000
0%
#65000
b10 .
1%
#70000
0%
#75000
b11 .
1%
#80000
0%
#85000
b100 .
1%
#90000
0%
#95000
b101 .
1%
#100000
0%
#105000
b110 .
1%
#110000
0%
#115000
b111 .
1%
#120000
0%
#125000
b1000 .
1%
#130000
0%
#135000
b1001 .
1%
#140000
0%
#145000
0!
b1010 .
1%
#150000
0%
#155000
b1011 .
1%
#160000
0%
#165000
b1100 .
1%
#170000
0%
#175000
b1101 .
1%
#180000
0%
#185000
b1110 .
1%
#190000
0%
#195000
b1111 .
1%
#200000
0%
#205000
b10000 .
1%
#210000
0%
#215000
b10001 .
1%
#220000
0%
#225000
b10010 .
1%
#230000
0%
#235000
b10011 .
1%
#240000
0%
#245000
1!
b0 .
1%
#250000
0%
#255000
b1 .
1%
#260000
0%
#265000
b10 .
1%
#270000
0%
#275000
b11 .
1%
#280000
0%
#285000
b100 .
1%
#290000
0%
#295000
b101 .
1%
#300000
0%
#305000
b110 .
1%
#310000
0%
#315000
b111 .
1%
#320000
0%
#325000
b1000 .
1%
#330000
0%
#335000
b1001 .
1%
#340000
0%
#345000
0!
b1010 .
1%
#350000
0%
#355000
b1011 .
1%
#360000
0%
#365000
b1100 .
1%
#370000
0%
#375000
b1101 .
1%
#380000
0%
#385000
b1110 .
1%
#390000
0%
#395000
b1111 .
1%
#400000
0%
#405000
b10000 .
1%
#410000
0%
#415000
b10001 .
1%
#420000
0%
#425000
b10010 .
1%
#430000
0%
#435000
b10011 .
1%
#440000
0%
#445000
1!
b0 .
1%
